MANIFEST.in
OLD_README.txt
setup.py
django_imaging.egg-info/PKG-INFO
django_imaging.egg-info/SOURCES.txt
django_imaging.egg-info/dependency_links.txt
django_imaging.egg-info/not-zip-safe
django_imaging.egg-info/requires.txt
django_imaging.egg-info/top_level.txt
imaging/__init__.py
imaging/__init__.pyc
imaging/admin.py
imaging/admin.pyc
imaging/fields.py
imaging/fields.pyc
imaging/forms.py
imaging/forms.pyc
imaging/models.py
imaging/models.pyc
imaging/tests.py
imaging/tests.pyc
imaging/urls.py
imaging/urls.pyc
imaging/views.py
imaging/views.pyc
imaging/widgets.py
imaging/widgets.pyc
imaging/fixtures/users.json
imaging/media/imaging/icon_changelink.gif
imaging/media/imaging/icon_deletelink.gif
imaging/media/imaging/imageselection.css
imaging/media/imaging/imageselection.js
imaging/media/imaging/imaging_testfile.jpg
imaging/media/imaging/jquery-1.3.2.min.js
imaging/media/imaging/jquery-ui-1.7.1.custom.min.js
imaging/media/imaging/jquery.json-1.3.min.js
imaging/media/imaging/nav-bg.gif
imaging/media/imaging/uploading.gif
imaging/templates/imaging/iframe_form.html