Metadata-Version: 1.1
Name: django-imaging
Version: 1.0.0
Summary: AJAX driven gallery field for django
Home-page: https://github.com/pielgrzym/django-imaging
Author: Jakub Nawalaniec
Author-email: pielgrzym@prymityw.pl
License: GNU GPL v2
Keywords: django
Platform: UNKNOWN
Classifier: Development Status :: 3 - Alpha
Classifier: Framework :: Django
Classifier: License :: OSI Approved :: GNU General Public License v2 (GPLv2)
